dataSaver/__init__.py
dataSaver-0.0.3.dist-info/METADATA
dataSaver-0.0.3.dist-info/WHEEL
dataSaver-0.0.3.dist-info/top_level.txt
dataSaver-0.0.3.dist-info/RECORD
