Metadata-Version: 2.1
Name: dataSaver
Version: 0.0.3
Summary: Utility to save data to cvs as an easy (and very basic) to read and use alternative to tensorboard
Home-page: https://github.com/Pensarfeo/dataSaver
Author: Pedro A. Favuzzi
Author-email: pa.favuzzi@gmail.com
License: UNKNOWN
Platform: UNKNOWN
Classifier: Programming Language :: Python :: 3
Classifier: License :: OSI Approved :: MIT License
Classifier: Operating System :: OS Independent
Requires-Dist: numpy
